README.md
setup.cfg
setup.py
climatempo/__init__.py
climatempo/climatempo.py
climatempo.egg-info/PKG-INFO
climatempo.egg-info/SOURCES.txt
climatempo.egg-info/dependency_links.txt
climatempo.egg-info/requires.txt
climatempo.egg-info/top_level.txt