Metadata-Version: 2.1
Name: climatempo
Version: 0.0.1
Summary: Simple wrapper for climatempo API (just to abstract home assistant)
Home-page: https://github.com/jblancoperez/climatempo
Author: Julio Manuel Blanco Perez
Author-email: jblancoperez@gmail.com
License: UNKNOWN
Platform: UNKNOWN
Classifier: Programming Language :: Python :: 3
Classifier: License :: OSI Approved :: MIT License
Classifier: Operating System :: OS Independent
